{
  "warehouse": {
    "warehouse_code": "CD34",
    "latitude": "-23.737696",
    "longitude": "-46.609861",
    "state": "SP" },
  "shipping_co": {
    "id": 1,
    "name": "Transportadora1",
    "corp_name": "Company1 S.A",
    "cnpj": "12345678910111",
    "address": "Rua teste, Nº 1 - Teste",
    "status": "active" },
  "customer": {
    "latitude": "-23.565821213904478",
    "longitude": "-46.65311298300678",
    "state": "SP",
    "validation_context": "nil",
    "errors": {} },
  "price": 1.0,
  "shipment_days": 1
}